dictionary/__init__.py
dictionary/dictionary.py
simple_cs453_homework1_dictionary_pasha-2.0.3.dist-info/METADATA
simple_cs453_homework1_dictionary_pasha-2.0.3.dist-info/WHEEL
simple_cs453_homework1_dictionary_pasha-2.0.3.dist-info/top_level.txt
simple_cs453_homework1_dictionary_pasha-2.0.3.dist-info/RECORD
