Metadata-Version: 2.1
Name: simple-cs453-homework1-dictionary-pasha
Version: 2.0.3
Summary: UNKNOWN
Author: Yusuf Alpdemir
License: UNKNOWN
Platform: UNKNOWN
Requires-Python: >=3.8
Requires-Dist: requests (>=2.23.0)
